{
  "kind": "collectionType",
  "collectionName": "articles",
  "info": {
    "singularName": "article",
    "pluralName": "articles",
    "displayName": "Article",
    "description": ""
  },
  "options": {
    "draftAndPublish": true
  },
  "pluginOptions": {},
  "attributes": {
    "Title": {
      "type": "string"
    },
    "image": {
      "type": "media",
      "multiple": false,
      "required": true,
      "allowedTypes": [
        "images",
        "files",
        "videos",
        "audios"
      ]
    },
    "Body": {
      "type": "richtext",
      "required": true
    },
    "slug": {
      "type": "uid",
      "targetField": "Title",
      "required": true
    },
    "article": {
      "type": "relation",
      "relation": "manyToOne",
      "target": "api::article.article",
      "inversedBy": "articles"
    },
    "articles": {
      "type": "relation",
      "relation": "oneToMany",
      "target": "api::article.article",
      "mappedBy": "article"
    }
  }
}
